srbai/__init__.py
srbai/test.py
srbai/Alati/Transliterator.py
srbai/Alati/__init__.py
srbai/Glas/__init__.py
srbai/JezickiModeli/__init__.py
srbai/JezickiModeli/FastText/__init__.py
srbai/JezickiModeli/FastText/__main__.py
srbai/JezickiModeli/FastText/embedding.py
srbai/JezickiModeli/FastText/globals.py
srbai/JezickiModeli/FastText/io_utils.py
srbai/JezickiModeli/FastText/model.py
srbai/JezickiModeli/FastText/similarity.py
srbai/JezickiModeli/FastText/text_preprocessing.py
srbai/Klasifikatori/__init__.py
srbai/NER/NER_classla.py
srbai/NER/__init__.py
srbai/Resursi/Modeli/model.hunpos.mte5.defnpout
srbai/Resursi/PomocneDatoteke/cygwin1.dll
srbai/Resursi/PomocneDatoteke/hunpos-tag
srbai/Resursi/PomocneDatoteke/hunpos-tag-lx
srbai/Resursi/PomocneDatoteke/hunpos-tag.exe
srbai/Resursi/PomocneDatoteke/hunpos-train
srbai/Resursi/PomocneDatoteke/hunpos-train-lx
srbai/Resursi/PomocneDatoteke/hunpos-train.exe
srbai/Resursi/Recnici/Serbian (Cyrillic).dic
srbai/Resursi/Recnici/Serbian (Cyrillic)_licence.txt
srbai/Resursi/Recnici/Serbian (Latin).dic
srbai/Resursi/Recnici/Serbian (Latin)_licence.txt
srbai/SintaktickiOperatori/POS_tagger.py
srbai/SintaktickiOperatori/__init__.py
srbai/SintaktickiOperatori/spellcheck.py
srbai/SintaktickiOperatori/stemmer_nm.py
SrbAI-0.0.19.dist-info/LICENSE
SrbAI-0.0.19.dist-info/METADATA
SrbAI-0.0.19.dist-info/WHEEL
SrbAI-0.0.19.dist-info/top_level.txt
SrbAI-0.0.19.dist-info/RECORD
