Metadata-Version: 2.1
Name: SrbAI
Version: 0.0.19
Summary: Library for processing serbian language
Home-page: https://github.com/Serbian-AI-Society/SrbAI
Author: Serbian AI Society
Author-email: nikola.milosevic86@gmail.com
Project-URL: Bug Tracker, https://github.com/Serbian-AI-Society/SrbAI/issues
Project-URL: Road Map, https://github.com/Serbian-AI-Society/SrbAI/projects/1
Classifier: Programming Language :: Python :: 3
Classifier: License :: OSI Approved :: GNU General Public License v3 or later (GPLv3+)
Classifier: Operating System :: OS Independent
Requires-Python: >=3.7
License-File: LICENSE
Requires-Dist: numpy
Requires-Dist: nltk
Requires-Dist: torch (>=1.10.2)
Requires-Dist: classla (==1.1.0)
Requires-Dist: nlu
